odoo/addons/helpdesk_motive/README.rst
odoo/addons/helpdesk_motive/__init__.py
odoo/addons/helpdesk_motive/__manifest__.py
odoo/addons/helpdesk_motive/i18n/es.po
odoo/addons/helpdesk_motive/i18n/es_AR.po
odoo/addons/helpdesk_motive/i18n/helpdesk_motive.pot
odoo/addons/helpdesk_motive/i18n/pt_BR.po
odoo/addons/helpdesk_motive/models/__init__.py
odoo/addons/helpdesk_motive/models/helpdesk_ticket.py
odoo/addons/helpdesk_motive/models/helpdesk_ticket_motive.py
odoo/addons/helpdesk_motive/readme/CONFIGURE.rst
odoo/addons/helpdesk_motive/readme/CONTRIBUTORS.rst
odoo/addons/helpdesk_motive/readme/DESCRIPTION.rst
odoo/addons/helpdesk_motive/readme/USAGE.rst
odoo/addons/helpdesk_motive/security/ir.model.access.csv
odoo/addons/helpdesk_motive/static/description/icon.png
odoo/addons/helpdesk_motive/static/description/index.html
odoo/addons/helpdesk_motive/views/helpdesk_ticket.xml
odoo/addons/helpdesk_motive/views/helpdesk_ticket_motive.xml
odoo13_addon_helpdesk_motive-13.0.1.0.1.dist-info/METADATA
odoo13_addon_helpdesk_motive-13.0.1.0.1.dist-info/WHEEL
odoo13_addon_helpdesk_motive-13.0.1.0.1.dist-info/top_level.txt
odoo13_addon_helpdesk_motive-13.0.1.0.1.dist-info/RECORD
